_django/__init__.py
_django/settings.py
_django/urls.py
_django/wsgi.py
kubernetes_manager/__init__.py
kubernetes_manager/admin.py
kubernetes_manager/apps.py
kubernetes_manager/consts.py
kubernetes_manager/urls.py
kubernetes_manager/utils.py
kubernetes_manager/migrations/0001_initial.py
kubernetes_manager/migrations/0002_auto_20200428_1836.py
kubernetes_manager/migrations/__init__.py
kubernetes_manager/models/__init__.py
kubernetes_manager/models/base.py
kubernetes_manager/models/kube.py
kubernetes_manager/models/mixins.py
kubernetes_manager/models/target_cluster.py
kubernetes_manager/serializers/__init__.py
kubernetes_manager/serializers/base.py
kubernetes_manager/tests/__init__.py
kubernetes_manager/tests/factories.py
kubernetes_manager/tests/test_cases.py
kubernetes_manager/views/__init__.py
kubernetes_manager/views/func_views.py
kubernetes_manager/views/model_views.py
django_kubernetes_manager-0.4.7.dist-info/LICENSE
django_kubernetes_manager-0.4.7.dist-info/METADATA
django_kubernetes_manager-0.4.7.dist-info/WHEEL
django_kubernetes_manager-0.4.7.dist-info/top_level.txt
django_kubernetes_manager-0.4.7.dist-info/RECORD
