Metadata-Version: 2.1
Name: django-kubernetes-manager
Version: 0.4.7
Summary: A Django app to manage kubernetes clusters and objects.
Home-page: UNKNOWN
Author: Bradley Reimers
Author-email: bradley@introspectdata.com
License: MIT
Project-URL: Documentation, https://django-kubernetes-manager.readthedocs.io/en/latest/
Project-URL: Sponsor, https://introspectdata.com
Project-URL: Source, https://github.com/IntrospectData/django-kubernetes-manager
Project-URL: Tracker, https://github.com/IntrospectData/django-kubernetes-manager/issues
Platform: UNKNOWN
Classifier: Environment :: Web Environment
Classifier: Framework :: Django
Classifier: Framework :: Django :: 3.0
Classifier: Intended Audience :: Developers
Classifier: License :: OSI Approved :: MIT License
Classifier: Operating System :: OS Independent
Classifier: Programming Language :: Python
Classifier: Programming Language :: Python :: 3
Classifier: Programming Language :: Python :: 3 :: Only
Classifier: Programming Language :: Python :: 3.6
Classifier: Programming Language :: Python :: 3.7
Classifier: Programming Language :: Python :: 3.8
Classifier: Topic :: Internet :: WWW/HTTP
Classifier: Topic :: Internet :: WWW/HTTP :: HTTP Servers
Classifier: Topic :: Internet :: WWW/HTTP :: Site Management
Requires-Dist: django-extensions
Requires-Dist: drf-yasg
Requires-Dist: djangorestframework
Requires-Dist: kubernetes
